<?xml version="1.0" encoding="UTF-8"?>
<objects serializationModel="Studio.02.02.00">
	<object class="Event" id="{d4eccfe7-053a-42f7-8def-b57b76fd7706}">
		<property name="name">
			<value>musicWithOUTLyrics</value>
		</property>
		<property name="outputFormat">
			<value>1</value>
		</property>
		<relationship name="folder">
			<destination>{5fc5398d-ab63-470a-91b9-a975421ff5a0}</destination>
		</relationship>
		<relationship name="mixer">
			<destination>{e73f51b4-66f5-4173-a16b-e986339ab466}</destination>
		</relationship>
		<relationship name="masterTrack">
			<destination>{3e484713-60a3-44e9-a125-5881b1fa79a6}</destination>
		</relationship>
		<relationship name="mixerInput">
			<destination>{5ee83705-3b20-48e0-b0e8-a65f409a7b89}</destination>
		</relationship>
		<relationship name="automatableProperties">
			<destination>{d8c7f3bb-d077-4f20-b7aa-2f92995e3fe5}</destination>
		</relationship>
		<relationship name="markerTracks">
			<destination>{0291d537-dd6d-4db2-bf1f-c9271d74c897}</destination>
		</relationship>
		<relationship name="groupTracks">
			<destination>{aa2b3b20-f348-4a09-a4a7-b7c31f6cdd33}</destination>
		</relationship>
		<relationship name="timeline">
			<destination>{c79f0661-8630-43f0-8afd-785824a60b83}</destination>
		</relationship>
		<relationship name="banks">
			<destination>{1bd6d03d-7db3-4004-b794-f561aa660181}</destination>
		</relationship>
	</object>
	<object class="EventMixer" id="{e73f51b4-66f5-4173-a16b-e986339ab466}">
		<relationship name="masterBus">
			<destination>{b8e0c937-7b0a-4986-86c3-e2b8a67facef}</destination>
		</relationship>
	</object>
	<object class="MasterTrack" id="{3e484713-60a3-44e9-a125-5881b1fa79a6}">
		<relationship name="mixerGroup">
			<destination>{b8e0c937-7b0a-4986-86c3-e2b8a67facef}</destination>
		</relationship>
	</object>
	<object class="MixerInput" id="{5ee83705-3b20-48e0-b0e8-a65f409a7b89}">
		<relationship name="effectChain">
			<destination>{04528f03-1c81-440b-b57a-4dc31947941b}</destination>
		</relationship>
		<relationship name="panner">
			<destination>{4ffdfb67-c267-4fe0-967a-8b32babf18ed}</destination>
		</relationship>
		<relationship name="output">
			<destination>{d259b378-dd09-40e0-a77e-b46eb8b718ae}</destination>
		</relationship>
	</object>
	<object class="EventAutomatableProperties" id="{d8c7f3bb-d077-4f20-b7aa-2f92995e3fe5}" />
	<object class="MarkerTrack" id="{0291d537-dd6d-4db2-bf1f-c9271d74c897}" />
	<object class="GroupTrack" id="{aa2b3b20-f348-4a09-a4a7-b7c31f6cdd33}">
		<relationship name="modules">
			<destination>{beefb805-8409-46ba-afae-1947b3a1bdbd}</destination>
			<destination>{b5b0fedc-800f-44d4-b7c4-c06937cc3b38}</destination>
		</relationship>
		<relationship name="mixerGroup">
			<destination>{c0f4f947-5584-4a04-b4ba-4969f6265aa2}</destination>
		</relationship>
	</object>
	<object class="Timeline" id="{c79f0661-8630-43f0-8afd-785824a60b83}">
		<relationship name="modules">
			<destination>{beefb805-8409-46ba-afae-1947b3a1bdbd}</destination>
			<destination>{b5b0fedc-800f-44d4-b7c4-c06937cc3b38}</destination>
		</relationship>
		<relationship name="markers">
			<destination>{c926aadb-ba3d-4ca1-994f-689e761fa827}</destination>
		</relationship>
	</object>
	<object class="EventMixerMaster" id="{b8e0c937-7b0a-4986-86c3-e2b8a67facef}">
		<relationship name="effectChain">
			<destination>{0f651e7d-0c1f-4226-960c-c8f175998f52}</destination>
		</relationship>
		<relationship name="panner">
			<destination>{4f0e64e6-28fc-43a7-b7cf-5f2d1def2bb1}</destination>
		</relationship>
		<relationship name="mixer">
			<destination>{e73f51b4-66f5-4173-a16b-e986339ab466}</destination>
		</relationship>
	</object>
	<object class="MixerBusEffectChain" id="{04528f03-1c81-440b-b57a-4dc31947941b}">
		<relationship name="effects">
			<destination>{75a10ed4-478d-489e-bf5c-49427e5b3139}</destination>
		</relationship>
	</object>
	<object class="MixerBusPanner" id="{4ffdfb67-c267-4fe0-967a-8b32babf18ed}" />
	<object class="SingleSound" id="{beefb805-8409-46ba-afae-1947b3a1bdbd}">
		<property name="length">
			<value>144</value>
		</property>
		<relationship name="audioFile">
			<destination>{13b1c901-bb5b-4231-8a97-65c6ad10b7db}</destination>
		</relationship>
	</object>
	<object class="SingleSound" id="{b5b0fedc-800f-44d4-b7c4-c06937cc3b38}">
		<property name="start">
			<value>144</value>
		</property>
		<property name="length">
			<value>104.72727891156462</value>
		</property>
		<relationship name="modulators">
			<destination>{dd936aea-5a18-42f0-9f42-a9bc0da6be77}</destination>
		</relationship>
		<relationship name="audioFile">
			<destination>{9677bb8c-df1f-4dc7-94a5-35ca6d7de71a}</destination>
		</relationship>
	</object>
	<object class="EventMixerGroup" id="{c0f4f947-5584-4a04-b4ba-4969f6265aa2}">
		<property name="volume">
			<value>-2</value>
		</property>
		<property name="name">
			<value>Audio 1</value>
		</property>
		<relationship name="effectChain">
			<destination>{cb9dd992-915f-4282-af42-4c5f36eb5ea0}</destination>
		</relationship>
		<relationship name="panner">
			<destination>{4a37940e-09ce-49ab-afc8-8bcb52b3a85e}</destination>
		</relationship>
		<relationship name="output">
			<destination>{b8e0c937-7b0a-4986-86c3-e2b8a67facef}</destination>
		</relationship>
	</object>
	<object class="LoopRegion" id="{c926aadb-ba3d-4ca1-994f-689e761fa827}">
		<property name="position">
			<value>144</value>
		</property>
		<property name="length">
			<value>104.72727891156461</value>
		</property>
		<relationship name="timeline">
			<destination>{c79f0661-8630-43f0-8afd-785824a60b83}</destination>
		</relationship>
		<relationship name="markerTrack">
			<destination>{0291d537-dd6d-4db2-bf1f-c9271d74c897}</destination>
		</relationship>
	</object>
	<object class="MixerBusEffectChain" id="{0f651e7d-0c1f-4226-960c-c8f175998f52}">
		<relationship name="effects">
			<destination>{1bb327c5-6b24-4af7-aa5d-c7b76e6e5171}</destination>
		</relationship>
	</object>
	<object class="MixerBusPanner" id="{4f0e64e6-28fc-43a7-b7cf-5f2d1def2bb1}" />
	<object class="MixerBusFader" id="{75a10ed4-478d-489e-bf5c-49427e5b3139}" />
	<object class="ADSRModulator" id="{dd936aea-5a18-42f0-9f42-a9bc0da6be77}">
		<property name="nameOfPropertyBeingModulated">
			<value>volume</value>
		</property>
		<property name="initialValue">
			<value>-80</value>
		</property>
		<property name="attackTime">
			<value>0</value>
		</property>
		<property name="releaseTime">
			<value>4000</value>
		</property>
		<property name="finalValue">
			<value>-80</value>
		</property>
	</object>
	<object class="MixerBusEffectChain" id="{cb9dd992-915f-4282-af42-4c5f36eb5ea0}">
		<relationship name="effects">
			<destination>{ba18ebc5-a6e8-46f4-90e7-d07449a0b999}</destination>
		</relationship>
	</object>
	<object class="MixerBusPanner" id="{4a37940e-09ce-49ab-afc8-8bcb52b3a85e}" />
	<object class="MixerBusFader" id="{1bb327c5-6b24-4af7-aa5d-c7b76e6e5171}" />
	<object class="MixerBusFader" id="{ba18ebc5-a6e8-46f4-90e7-d07449a0b999}" />
</objects>
